MANIFEST.in
README.md
install.json
pyproject.toml
setup.cfg
setup.py
js/.DS_Store
js/README.md
js/package.json
js/webpack.config.js
js/yarn.lock
js/dist/index.js
js/dist/index.js.LICENSE.txt
js/lib/embed.js
js/lib/example.js
js/lib/extension.js
js/lib/index.js
js/lib/labplugin.js
js/lib/style.css
js/lib/widgetfunctions.js
pandaspraxis/Translator.py
pandaspraxis/TranslatorTests.py
pandaspraxis/__init__.py
pandaspraxis/_version.py
pandaspraxis/example.py
pandaspraxis/sample_user.py
pandaspraxis.egg-info/PKG-INFO
pandaspraxis.egg-info/SOURCES.txt
pandaspraxis.egg-info/dependency_links.txt
pandaspraxis.egg-info/not-zip-safe
pandaspraxis.egg-info/requires.txt
pandaspraxis.egg-info/top_level.txt
pandaspraxis/labextension/package.json
pandaspraxis/labextension/static/261.9c013c7b68845c0f7b9a.js
pandaspraxis/labextension/static/486.39f66f9023780ca9fd89.js
pandaspraxis/labextension/static/486.39f66f9023780ca9fd89.js.LICENSE.txt
pandaspraxis/labextension/static/568.fcb9e649558e1780d93b.js
pandaspraxis/labextension/static/remoteEntry.dd100f42a2ff27ad53e9.js
pandaspraxis/labextension/static/style.js
pandaspraxis/nbextension/extension.js
pandaspraxis/nbextension/index.js
pandaspraxis/nbextension/index.js.LICENSE.txt